setup.cfg
setup.py
cronen/__init__.py
cronen/base.py
cronen/scheduler.py
cronen/trigger.py
cronen.egg-info/PKG-INFO
cronen.egg-info/SOURCES.txt
cronen.egg-info/dependency_links.txt
cronen.egg-info/requires.txt
cronen.egg-info/top_level.txt
cronen/tests/__init__.py
cronen/tests/cronen/__init__.py
cronen/tests/cronen/test_scheduler.py
cronen/tests/cronen/test_trigger.py