Metadata-Version: 1.1
Name: cronen
Version: 1.1
Summary: A mini cron library for python. Allows scheduling jobs on a single node and provides a simple web interface for monitoring and manual triggering.
Home-page: https://github.com/barakschiller/cronen
Author: Barak Schiller
Author-email: bschiller@gmail.com
License: UNKNOWN
Download-URL: https://github.com/barakschiller/cronen/tarball/1.0
Keywords: cron
Platform: UNKNOWN
